igpu/__init__.py
igpu/core.py
igpu/gpu_info.py
igpu/parser.py
igpu-0.1.2.dist-info/LICENSE
igpu-0.1.2.dist-info/METADATA
igpu-0.1.2.dist-info/WHEEL
igpu-0.1.2.dist-info/top_level.txt
igpu-0.1.2.dist-info/RECORD
