Metadata-Version: 2.1
Name: igpu
Version: 0.1.2
Summary: A cross-platform module for retrieving information and stats on installed gpus.
Home-page: http://github.com/acnazarejr/igpu
Author: Antonio Carlos Nazare Jr.
Author-email: antonio.nazare@dcc.ufmg.br
Maintainer: Antonio Carlos Nazare Jr.
Maintainer-email: antonio.nazare@dcc.ufmg.br
License: UNKNOWN
Download-URL: http://github.com/acnazarejr/igpu
Keywords: gpu cuda nvidia
Platform: UNKNOWN
Classifier: Development Status :: 5 - Production/Stable
Classifier: Environment :: Console
Classifier: Intended Audience :: Developers
Classifier: License :: OSI Approved :: MIT License
Classifier: Intended Audience :: Developers
Classifier: Intended Audience :: Education
Classifier: Intended Audience :: End Users/Desktop
Classifier: Intended Audience :: Other Audience
Classifier: Intended Audience :: System Administrators
Classifier: Natural Language :: English
Classifier: Operating System :: Microsoft :: Windows :: Windows 10
Classifier: Operating System :: Microsoft :: Windows :: Windows 7
Classifier: Operating System :: Microsoft :: Windows :: Windows 8
Classifier: Operating System :: Microsoft :: Windows :: Windows 8.1
Classifier: Operating System :: POSIX :: Linux
Classifier: Programming Language :: Python :: 3.4
Classifier: Programming Language :: Python :: 3.5
Classifier: Programming Language :: Python :: 3.6
Classifier: Programming Language :: Python :: 3.7
Classifier: Topic :: Software Development :: Libraries
Requires-Python: >=3.4
